alphafold3_polymer_bonds/__init__.py
alphafold3_polymer_bonds/alphafold3_io.py
alphafold3_polymer_bonds/main.py
alphafold3_polymer_bonds/data/alphafold3_get_ccd.py
alphafold3_polymer_bonds/data/polybonds.cif
alphafold3_polymer_bonds/data/polybonds.json
alphafold3_polymer_bonds/data/visualise_cif.ipynb
alphafold3_polymer_bonds-0.3.dist-info/METADATA
alphafold3_polymer_bonds-0.3.dist-info/WHEEL
alphafold3_polymer_bonds-0.3.dist-info/entry_points.txt
alphafold3_polymer_bonds-0.3.dist-info/licenses/LICENSE
alphafold3_polymer_bonds-0.3.dist-info/RECORD
