Metadata-Version: 2.4
Name: alphafold3-polymer-bonds
Version: 0.3
Summary: Support for covalent bonds between/within polymer chains (protein, DNA, RNA) in AlphaFold3
Project-URL: Homepage, https://github.com/jurgjn/alphafold3-polymer-bonds
Project-URL: Issues, https://github.com/jurgjn/alphafold3-polymer-bonds/issues
Author-email: jurgjn <jurgjn@users.noreply.github.com>
License-Expression: CC-BY-NC-SA-4.0
License-File: LICENSE
Classifier: Development Status :: 3 - Alpha
Classifier: Operating System :: OS Independent
Classifier: Programming Language :: Python :: 3
Requires-Python: >=3.9
Requires-Dist: biopython
Requires-Dist: humanfriendly
Requires-Dist: pandas
Requires-Dist: py3dmol
